jonbot/__init__.py
jonbot/__main__.py
jonbot/layer0_frontends/__init__.py
jonbot/layer0_frontends/discord_bot/__init__.py
jonbot/layer0_frontends/discord_bot/cogs/__init__.py
jonbot/layer0_frontends/discord_bot/cogs/legacy/chat_cog/__init__.py
jonbot/layer0_frontends/discord_bot/cogs/legacy/chat_cog/chat_cog.py
jonbot/layer0_frontends/discord_bot/cogs/legacy/chat_cog/chat_model.py
jonbot/layer0_frontends/discord_bot/cogs/legacy/chat_cog/update_discord_message_callback_manager.py
jonbot/layer0_frontends/discord_bot/cogs/legacy/thread_scraper_cog/__init__.py
jonbot/layer0_frontends/discord_bot/cogs/legacy/thread_scraper_cog/message_anonymizer.py
jonbot/layer0_frontends/discord_bot/cogs/legacy/thread_scraper_cog/thread_scraper_cog.py
jonbot/layer0_frontends/discord_bot/cogs/legacy/thread_scraper_cog/thread_stats.py
jonbot/layer0_frontends/discord_bot/discord_client.py
jonbot/layer0_frontends/discord_bot/discord_main.py
jonbot/layer0_frontends/discord_bot/event_handlers/__init__.py
jonbot/layer0_frontends/discord_bot/event_handlers/handle_text_message.py
jonbot/layer0_frontends/discord_bot/event_handlers/handle_voice_memo.py
jonbot/layer0_frontends/telegram_bot/__init__.py
jonbot/layer0_frontends/telegram_bot/handlers/__init__.py
jonbot/layer0_frontends/telegram_bot/handlers/audio_to_text.py
jonbot/layer0_frontends/telegram_bot/handlers/telegram_chat.py
jonbot/layer0_frontends/telegram_bot/telegram_bot.py
jonbot/layer1_api_interface/__init__.py
jonbot/layer1_api_interface/app.py
jonbot/layer2_core_processes/__init__.py
jonbot/layer2_core_processes/ai_chatbot/__init__.py
jonbot/layer2_core_processes/ai_chatbot/ai_chatbot.py
jonbot/layer2_core_processes/ai_chatbot/ai_chatbot_prompts.py
jonbot/layer2_core_processes/ai_chatbot/utilities/__init__.py
jonbot/layer2_core_processes/ai_chatbot/utilities/streaming_message_handler.py
jonbot/layer2_core_processes/audio_transcription/__init__.py
jonbot/layer2_core_processes/audio_transcription/transcribe_audio.py
jonbot-0.1.0.dist-info/LICENSE
jonbot-0.1.0.dist-info/METADATA
jonbot-0.1.0.dist-info/WHEEL
jonbot-0.1.0.dist-info/RECORD
