Metadata-Version: 2.1
Name: jonbot
Version: 0.1.0
Summary: a friendly machine 🤖❤️✨
License: AGPLv3+
Author: jonmatthis
Author-email: jonmatthis@gmail.com
Requires-Python: >=3.9,<4.0
Classifier: License :: Other/Proprietary License
Classifier: Programming Language :: Python :: 3
Classifier: Programming Language :: Python :: 3.9
Classifier: Programming Language :: Python :: 3.10
Classifier: Programming Language :: Python :: 3.11
Requires-Dist: aiohttp (>=3.8.5,<4.0.0)
Requires-Dist: chromadb (>=0.4.3,<0.5.0)
Requires-Dist: discord.py (>=2.3.1,<3.0.0)
Requires-Dist: fastapi (<0.100.0)
Requires-Dist: langchain (>=0.0.246,<0.0.247)
Requires-Dist: logging (>=0.4.9.6,<0.5.0.0)
Requires-Dist: mkdocs-material (>=9.1.19,<10.0.0)
Requires-Dist: openai (>=0.27.8,<0.28.0)
Requires-Dist: pydantic (<2)
Requires-Dist: pydub (>=0.25.1,<0.26.0)
Requires-Dist: pymongo (>=4.4.1,<5.0.0)
Requires-Dist: python-dotenv (>=1.0.0,<2.0.0)
Requires-Dist: rich (>=13.4.2,<14.0.0)
Requires-Dist: tiktoken (>=0.4.0,<0.5.0)
Requires-Dist: tzlocal (>=5.0.1,<6.0.0)
Requires-Dist: uvicorn (>=0.23.1,<0.24.0)
